Metadata-Version: 1.1
Name: travis-pypi-deploy-test
Version: 0.1
Summary: Testing auto deplyoment to pypi via travis CI
Home-page: UNKNOWN
Author: Stephen De Vight
Author-email: yourname@example.com
License: UNKNOWN
Platform: UNKNOWN
Classifier: Intended Audience :: Developers
Classifier: Operating System :: OS Independent
Classifier: Programming Language :: Python
